gxb/__init__.py
gxb/exceptions.py
gxb/api/__init__.py
gxb/api/block.py
gxb-0.1.0.dist-info/DESCRIPTION.rst
gxb-0.1.0.dist-info/METADATA
gxb-0.1.0.dist-info/RECORD
gxb-0.1.0.dist-info/WHEEL
gxb-0.1.0.dist-info/metadata.json
gxb-0.1.0.dist-info/top_level.txt
