Metadata-Version: 2.0
Name: gxb
Version: 0.1.0
Summary: GXB Python SDK
Home-page: https://github.com/zjhmale/gxb.py
Author: zjhmale
Author-email: zjhsdtc@gmail.com
License: MIT
Keywords: GXB GXShare
Platform: UNKNOWN
Classifier: Intended Audience :: Developers
Classifier: License :: OSI Approved :: MIT License
Classifier: Operating System :: OS Independent
Classifier: Programming Language :: Python :: 2
Classifier: Programming Language :: Python :: 2.7
Classifier: Programming Language :: Python :: 3
Classifier: Programming Language :: Python :: 3.4
Classifier: Programming Language :: Python :: 3.5
Classifier: Programming Language :: Python :: 3.6
Classifier: Programming Language :: Python
Classifier: Topic :: Software Development :: Libraries :: Python Modules
Requires-Dist: ndg-httpsclient
Requires-Dist: pyOpenSSL
Requires-Dist: pyasn1
Requires-Dist: requests
